matx/__init__.py
matx/_hooks.py
matx/_typed_ast.py
matx/build_info
matx/env.py
matx/error.py
matx/toolchain.py
matx/tutorial.py
matx/typing.py
matx/_ffi/__init__.py
matx/_ffi/_pyversion.py
matx/_ffi/_selector.py
matx/_ffi/base.py
matx/_ffi/error.py
matx/_ffi/libinfo.py
matx/_ffi/registry.py
matx/_ffi/runtime_ctypes.py
matx/_ffi/_c_ext/__init__.py
matx/_ffi/_c_ext/_loader.py
matx/_ffi/_c_ext/fast_c_api.cc
matx/_ffi/_c_ext/matx_script_api.so
matx/_ffi/_c_ext/object.py
matx/_ffi/_c_ext/packed_func.py
matx/_ffi/_c_ext/types.py
matx/cfg/__init__.py
matx/cfg/builder.py
matx/cfg/model.py
matx/contrib/__init__.py
matx/contrib/_filelock.py
matx/contrib/cc.py
matx/contrib/cpp_extension.py
matx/contrib/inspect3_9_1_patch.py
matx/contrib/ndk.py
matx/contrib/statistic.py
matx/contrib/tar.py
matx/contrib/util.py
matx/extension/__init__.py
matx/extension/cpp/pytorch/CMakeLists.txt
matx/extension/cpp/pytorch/src/matx_inc.h
matx/extension/cpp/pytorch/src/tensor_api.cc
matx/extension/cpp/pytorch/src/torch_inc.h
matx/extension/cpp/pytorch/src/torch_infer_op.cc
matx/extension/cpp/pytorch/src/torch_infer_op.h
matx/extension/cpp/pytorch/src/torch_model.cc
matx/extension/cpp/pytorch/src/torch_model.h
matx/extension/cpp/tensorflow/CMakeLists.txt
matx/extension/cpp/tensorflow/src/_tensorflow_cc_savedmodel_constants.h
matx/extension/cpp/tensorflow/src/_tensorflow_cc_savedmodel_reader.h
matx/extension/cpp/tensorflow/src/_tensorflow_cc_savedmodel_signature_constants.h
matx/extension/cpp/tensorflow/src/_tensorflow_cc_savedmodel_tag_constants.h
matx/extension/cpp/tensorflow/src/tf_dataset_callback_op.cc
matx/extension/cpp/tensorflow/src/tf_dataset_callback_op.h
matx/extension/cpp/tensorflow/src/tf_infer_op.cc
matx/extension/cpp/tensorflow/src/tf_infer_op.h
matx/extension/cpp/tensorflow/src/tf_model.cc
matx/extension/cpp/tensorflow/src/tf_model.h
matx/extension/cpp/tensorflow/src/tf_utils.cc
matx/extension/cpp/tensorflow/src/tf_utils.h
matx/extension/cpp/tvm/CMakeLists.txt
matxscript-1.8.1.dist-info/METADATA
matxscript-1.8.1.dist-info/WHEEL
matxscript-1.8.1.dist-info/top_level.txt
matxscript-1.8.1.dist-info/RECORD
