Metadata-Version: 2.1
Name: matxscript
Version: 1.8.1
Summary: Static Python AOT Compiler
Home-page: https://github.com/bytedance/matxscript
Author: MATXScript Team
Author-email: maxiandi@bytedance.com
License: UNKNOWN
Platform: UNKNOWN
Requires-Python: >=3.6
Requires-Dist: numpy (<2.0.0,>=1.6)
Requires-Dist: typed-ast (<2.0)
Requires-Dist: astpretty (<3.0.0,>=1.0)
Requires-Dist: prettytable (<4.0.0,>=1.0)
